LICENSE
MANIFEST.in
README.md
VERSION
requirements.txt
setup.py
bert_onnx/__init__.py
bert_onnx/bert_onnx.py
bert_onnx.egg-info/PKG-INFO
bert_onnx.egg-info/SOURCES.txt
bert_onnx.egg-info/dependency_links.txt
bert_onnx.egg-info/requires.txt
bert_onnx.egg-info/top_level.txt